youtube_collector/__init__.py
youtube_collector/client.py
youtube_collector/config.py
dacquaviva_youtube_collector-0.7.0.dist-info/METADATA
dacquaviva_youtube_collector-0.7.0.dist-info/WHEEL
dacquaviva_youtube_collector-0.7.0.dist-info/top_level.txt
dacquaviva_youtube_collector-0.7.0.dist-info/RECORD
