Metadata-Version: 2.4
Name: dacquaviva-youtube-collector
Version: 0.7.0
Summary: A library for collecting video data from YouTube.
Author-email: Daniele Acquaviva <danieleacquaviva96@gmail.com>
License: MIT
Project-URL: Homepage, https://github.com/yourusername/youtube-thumbnails
Project-URL: Repository, https://github.com/yourusername/youtube-thumbnails
Keywords: youtube,data collection,video,thumbnails
Classifier: Development Status :: 3 - Alpha
Classifier: Intended Audience :: Developers
Classifier: License :: OSI Approved :: MIT License
Classifier: Programming Language :: Python :: 3
Classifier: Programming Language :: Python :: 3.8
Classifier: Programming Language :: Python :: 3.9
Classifier: Programming Language :: Python :: 3.10
Classifier: Programming Language :: Python :: 3.11
Requires-Python: >=3.8
Requires-Dist: google-api-python-client>=2.0.0
Requires-Dist: requests>=2.25.1
Requires-Dist: numpy>=1.20.0
Provides-Extra: dev
Requires-Dist: pytest>=7.0.0; extra == "dev"
Requires-Dist: pytest-cov>=4.0.0; extra == "dev"
Requires-Dist: build>=0.10.0; extra == "dev"
